README.rst
keyserver.py
setup.cfg
setup.py
keyserver/__init__.py
keyserver/generator.py
keyserver.egg-info/PKG-INFO
keyserver.egg-info/SOURCES.txt
keyserver.egg-info/dependency_links.txt
keyserver.egg-info/entry_points.txt
keyserver.egg-info/top_level.txt