Metadata-Version: 1.1
Name: keyserver
Version: 1.0.0.3
Summary: Command line Pub key generator from keyserver.ubuntu.com
Home-page: https://codecumulus13.wordpress.com
Author: Laode Hadi Cahyadi
Author-email: licface@yahoo.com
License: MIT
Download-URL: https://github.com/cumulus13/keyserver/archive/v1.0(t0.3).tar.gz
Keywords: keyserver,cli,command line
Platform: any
Classifier: Environment :: Console
Classifier: Intended Audience :: Developers
Classifier: Intended Audience :: Information Technology
Classifier: Development Status :: 3 - Alpha
Classifier: License :: OSI Approved :: MIT License
Classifier: Programming Language :: Python :: 2.6
Classifier: Programming Language :: Python :: 2.7
Classifier: Topic :: Text Processing :: General
Classifier: Topic :: Software Development :: Libraries :: Python Modules
Classifier: Topic :: System :: Software Distribution
Classifier: Topic :: Utilities
Classifier: Operating System :: OS Independent
